superset_mcp_server/mcp_methods.json
superset_mcp_server/mcp_server.py
superset_mcp_server/open_api_spec_parser.py
superset_mcp_server/openapi_spec.json
superset_mcp_server/superset_client.py
superset_mcp_server-0.1.0a5.dist-info/LICENSE
superset_mcp_server-0.1.0a5.dist-info/METADATA
superset_mcp_server-0.1.0a5.dist-info/WHEEL
superset_mcp_server-0.1.0a5.dist-info/RECORD
