Metadata-Version: 2.3
Name: superset-mcp-server
Version: 0.1.0a5
Summary: An MCP server for Apache Superset that dynamically exposes API endpoints as tools.
License: MIT
Author: Hipposys
Requires-Python: >=3.10,<4.0
Classifier: License :: OSI Approved :: MIT License
Classifier: Programming Language :: Python :: 3
Classifier: Programming Language :: Python :: 3.10
Classifier: Programming Language :: Python :: 3.11
Classifier: Programming Language :: Python :: 3.12
Classifier: Programming Language :: Python :: 3.13
Requires-Dist: fastapi (>=0.115.0,<0.116.0)
Requires-Dist: httpx (>=0.28.0,<0.29.0)
Requires-Dist: mcp[cli] (<2.0)
Requires-Dist: requests (>=2.32.0,<3.0.0)
Requires-Dist: starlette (>=0.37.0,<0.38.0)
Requires-Dist: uvicorn (>=0.34.0,<0.35.0)
Project-URL: homepage, https://github.com/your-org/your-repo
